Workbook

Sheet Supuestos
A1: SUPUESTOS DEL MODELO FINANCIERO - SMARTPHARM CRM
A2: Valores en AZUL son inputs modificables | Valores en NEGRO son calculados
A4: PARÁMETROS FINANCIEROS
A5: Parámetro | B5: Valor | C5: Unidad | D5: Justificación
A6: Tasa libre de riesgo | B6: 0.05 | C6: % | D6: Bonos BCCh 10 años (2025)
A7: Prima riesgo mercado | B7: 0.04 | C7: % | D7: Prima moderada mercado chileno
A8: Prima riesgo startup | B8: 0.03 | C8: % | D8: MVP validado, datos reales, equipo técnico
A9: TREMA (calculada) | B9: =B6+B7+B8 -> 0.12 | C9: % | D9: Suma componentes CAPM ajustado
A10: Horizonte evaluación | B10: 5 | C10: años | D10: Estándar SaaS B2B
A11: Inversión inicial efectivo | B11: 9500000 | C11: CLP | D11: Infraestructura ($500k) + Capital trabajo 6 meses ($9M)
A13: PARÁMETROS COMERCIALES
A14: Parámetro | B14: Valor | C14: Unidad | D14: Justificación
A15: Precio mensual sin IVA | B15: 18000 | C15: CLP/mes | D15: 75% menor que competencia
A16: Tasa conversión freemium | B16: 0.2 | C16: % | D16: Estándar industria SaaS
A17: Tasa retención anual | B17: 0.8 | C17: % | D17: Conservador (industria 85-90%)
A18: Tasa churn anual | B18: =1-B17 -> 0.2 | C18: % | D18: Complemento retención
A19: Ingreso anual por cliente | B19: =B15*12 -> 216000 | C19: CLP/año | D19: Precio × 12 meses
A22: PROYECCIÓN DE CLIENTES
A23: Año | B23: Clientes | C23: Crecimiento | D23: Justificación
A24: 1 | B24: 35 | C24: - | D24: Piloto + marketing inicial
A25: 2 | B25: 60 | C25: =B25/B24-1 -> 0.71428571 | D25: Retención 80% + 32 nuevos
A26: 3 | B26: 90 | C26: =B26/B25-1 -> 0.5 | D26: Escala + vendedor comercial
A27: 4 | B27: 130 | C27: =B27/B26-1 -> 0.44444444 | D27: Expansión regional
A28: 5 | B28: 170 | C28: =B28/B27-1 -> 0.30769231 | D28: Consolidación mercado
A30: Mercado total farmacias pequeñas Chile | B30: 3200 | C30: Fuente: Asociación de Farmacias Chile
A31: Penetración año 5 | B31: =B27/B30 -> 0.040625

Sheet Costos Operacionales
A1: COSTOS OPERACIONALES PROYECTADOS
A2: Todas las cifras en CLP | Fórmulas vinculadas a Supuestos
A4: Categoría | B4: Año 1 | C4: Año 2 | D4: Año 3 | E4: Año 4 | F4: Año 5 | G4: Notas
A5: Infraestructura nube | B5: 1420000 | C5: =B5*1.38 -> 1959600 | D5: =C5*1.48 -> 2900208 | E5: =D5*1.2 -> 3480249.6 | F5: =E5*1.2 -> 4176299.5 | G5: Escala con clientes
A6: Personal y servicios | B6: 3700000 | C6: 5250000 | D6: 9150000 | E6: 10530000 | F6: 12061000 | G6: Contrataciones según crecimiento
A7: Marketing digital | B7: 3300000 | C7: 1990000 | D7: 2175000 | E7: 2363000 | F7: 2556000 | G7: Año 1 incluye $2M lanzamiento (one-time)
A8: Gastos administrativos | B8: 1580000 | C8: 296000 | D8: 417000 | E8: 551000 | F8: 717000 | G8: Año 1 incluye $1.5M legal (one-time)
A9: TOTAL COSTOS | B9: =SUM(B5:B8) -> 10000000 | C9: =SUM(C5:C8) -> 9495600 | D9: =SUM(D5:D8) -> 14642208 | E9: =SUM(E5:E8) -> 16924250 | F9: =SUM(F5:F8) -> 19510300
A11: Costo por cliente/año | B11: =B9/Supuestos!B24 -> 285714.29 | C11: =C9/Supuestos!B25 -> 158260 | D11: =D9/Supuestos!B26 -> 162691.2 | E11: =E9/Supuestos!B27 -> 130186.54 | F11: =F9/Supuestos!B28 -> 114766.47

Sheet Flujo de Caja
A1: FLUJO DE CAJA PROYECTADO
A3: Concepto | B3: Año 0 | C3: Año 1 | D3: Año 2 | E3: Año 3 | F3: Año 4 | G3: Año 5
A4: INVERSIÓN INICIAL | B4: =-Supuestos!B11 -> -9500000 | C4: 0 | D4: 0 | E4: 0 | F4: 0 | G4: 0
A6: Clientes activos | C6: =Supuestos!B24 -> 35 | D6: =Supuestos!B25 -> 60 | E6: =Supuestos!B26 -> 90 | F6: =Supuestos!B27 -> 130 | G6: =Supuestos!B28 -> 170
A7: Ingreso por cliente | C7: =Supuestos!B19 -> 216000 | D7: =Supuestos!B19 -> 216000 | E7: =Supuestos!B19 -> 216000 | F7: =Supuestos!B19 -> 216000 | G7: =Supuestos!B19 -> 216000
A8: INGRESOS OPERACIONALES | B8: 0 | C8: =C6*C7 -> 7560000 | D8: =D6*D7 -> 12960000 | E8: =E6*E7 -> 19440000 | F8: =F6*F7 -> 28080000 | G8: =G6*G7 -> 36720000
A10: COSTOS OPERACIONALES | B10: 0 | C10: ='Costos Operacionales'!B9 -> 10000000 | D10: ='Costos Operacionales'!C9 -> 9495600 | E10: ='Costos Operacionales'!D9 -> 14642208 | F10: ='Costos Operacionales'!E9 -> 16924250 | G10: ='Costos Operacionales'!F9 -> 19510300
A12: FLUJO NETO | B12: =B4 -> -9500000 | C12: =C8-C10 -> -2440000 | D12: =D8-D10 -> 3464400 | E12: =E8-E10 -> 4797792 | F12: =F8-F10 -> 11155750 | G12: =G8-G10 -> 17209700
A14: FLUJO ACUMULADO | B14: =B12 -> -9500000 | C14: =B14+C12 -> -11940000 | D14: =C14+D12 -> -8475600 | E14: =D14+E12 -> -3677808 | F14: =E14+F12 -> 7477942.4 | G14: =F14+G12 -> 24687643

Sheet VAN y TIR
A1: EVALUACIÓN FINANCIERA - VAN Y TIR
A3: PARÁMETROS
A4: TREMA (tasa descuento) | B4: =Supuestos!B9 -> 0.12 | C4: ← Calculada desde componentes CAPM
A5: Inversión inicial | B5: =Supuestos!B11 -> 9500000
A7: FLUJOS DESCONTADOS
A8: Año | B8: Flujo Neto | C8: Factor (1+r)^t | D8: Valor Presente
A9: 0 | B9: ='Flujo de Caja'!B12 -> -9500000 | C9: =1 -> 1 | D9: =B9*C9 -> -9500000
A10: 1 | B10: ='Flujo de Caja'!C12 -> -2440000 | C10: =(1+$B$4)^A10 -> 1.12 | D10: =B10/C10 -> -2178571.4
A11: 2 | B11: ='Flujo de Caja'!D12 -> 3464400 | C11: =(1+$B$4)^A11 -> 1.2544 | D11: =B11/C11 -> 2761798.5
A12: 3 | B12: ='Flujo de Caja'!E12 -> 4797792 | C12: =(1+$B$4)^A12 -> 1.404928 | D12: =B12/C12 -> 3414973.6
A13: 4 | B13: ='Flujo de Caja'!F12 -> 11155750 | C13: =(1+$B$4)^A13 -> 1.5735194 | D13: =B13/C13 -> 7089681.1
A14: 5 | B14: ='Flujo de Caja'!G12 -> 17209700 | C14: =(1+$B$4)^A14 -> 1.7623417 | D14: =B14/C14 -> 9765246.2
A16: VAN (Valor Actual Neto) | B16: =SUM(D9:D14) -> 11353128 | C16: ← Si VAN > 0, proyecto viable
A17: TIR (Tasa Interna Retorno) | B17: =IRR(B9:B14) -> 0.34147595 | C17: ← Si TIR > TREMA, proyecto rentable
A19: INTERPRETACIÓN
A20: Diferencial TIR - TREMA | B20: =B17-B4 -> 0.22147595 | C20: Margen de seguridad sobre costo de oportunidad
A21: Decisión | B21: =IF(AND(B16>0,B17>B4),"VIABLE","NO VIABLE") -> VIABLE

Sheet Sensibilidad
A1: ANÁLISIS DE SENSIBILIDAD
A2: ¿Cómo cambia el VAN con diferentes tasas de descuento?
A4: SENSIBILIDAD A TASA DE DESCUENTO
A5: TREMA | B5: VAN | C5: Decisión
A6: 0.1 | B6: ='Flujo de Caja'!B12 + 'Flujo de Caja'!C12/(1+A6)^1 + 'Flujo de Caja'!D12/(1+A6)^2 + 'Flujo de Caja'!E12/(1+A6)^3 + 'Flujo de Caja'!F12/(1+A6)^4 + 'Flujo de Caja'!G12/(1+A6)^5 -> 13055008 | C6: =IF(B6>0,"VIABLE","NO VIABLE") -> VIABLE
A7: 0.12 | B7: ='Flujo de Caja'!B12 + 'Flujo de Caja'!C12/(1+A7)^1 + 'Flujo de Caja'!D12/(1+A7)^2 + 'Flujo de Caja'!E12/(1+A7)^3 + 'Flujo de Caja'!F12/(1+A7)^4 + 'Flujo de Caja'!G12/(1+A7)^5 -> 11353128 | C7: =IF(B7>0,"VIABLE","NO VIABLE") -> VIABLE
A8: 0.15 | B8: ='Flujo de Caja'!B12 + 'Flujo de Caja'!C12/(1+A8)^1 + 'Flujo de Caja'!D12/(1+A8)^2 + 'Flujo de Caja'!E12/(1+A8)^3 + 'Flujo de Caja'!F12/(1+A8)^4 + 'Flujo de Caja'!G12/(1+A8)^5 -> 9087070.3 | C8: =IF(B8>0,"VIABLE","NO VIABLE") -> VIABLE
A9: 0.18 | B9: ='Flujo de Caja'!B12 + 'Flujo de Caja'!C12/(1+A9)^1 + 'Flujo de Caja'!D12/(1+A9)^2 + 'Flujo de Caja'!E12/(1+A9)^3 + 'Flujo de Caja'!F12/(1+A9)^4 + 'Flujo de Caja'!G12/(1+A9)^5 -> 7116896.5 | C9: =IF(B9>0,"VIABLE","NO VIABLE") -> VIABLE
A10: 0.2 | B10: ='Flujo de Caja'!B12 + 'Flujo de Caja'!C12/(1+A10)^1 + 'Flujo de Caja'!D12/(1+A10)^2 + 'Flujo de Caja'!E12/(1+A10)^3 + 'Flujo de Caja'!F12/(1+A10)^4 + 'Flujo de Caja'!G12/(1+A10)^5 -> 5945087.7 | C10: =IF(B10>0,"VIABLE","NO VIABLE") -> VIABLE
A11: 0.22 | B11: ='Flujo de Caja'!B12 + 'Flujo de Caja'!C12/(1+A11)^1 + 'Flujo de Caja'!D12/(1+A11)^2 + 'Flujo de Caja'!E12/(1+A11)^3 + 'Flujo de Caja'!F12/(1+A11)^4 + 'Flujo de Caja'!G12/(1+A11)^5 -> 4873049.1 | C11: =IF(B11>0,"VIABLE","NO VIABLE") -> VIABLE
A12: 0.25 | B12: ='Flujo de Caja'!B12 + 'Flujo de Caja'!C12/(1+A12)^1 + 'Flujo de Caja'!D12/(1+A12)^2 + 'Flujo de Caja'!E12/(1+A12)^3 + 'Flujo de Caja'!F12/(1+A12)^4 + 'Flujo de Caja'!G12/(1+A12)^5 -> 3430355.5 | C12: =IF(B12>0,"VIABLE","NO VIABLE") -> VIABLE
A14: Fila amarilla = TREMA seleccionada en el modelo (20%)
A17: SENSIBILIDAD A NÚMERO DE CLIENTES AÑO 5
A18: Clientes Año 5 | B18: VAN estimado | C18: Variación
A19: 100 | B19: Ver nota | C19: -41% clientes
A20: 130 | B20: Ver nota | C20: -24% clientes
A21: 150 | B21: Ver nota | C21: -12% clientes
A22: 170 | B22: Ver nota | C22: Base
A23: 200 | B23: Ver nota | C23: +18% clientes
A24: 230 | B24: Ver nota | C24: +35% clientes
A26: Nota: Para análisis completo, modificar clientes en hoja Supuestos

Sheet Punto Equilibrio
A1: ANÁLISIS DE PUNTO DE EQUILIBRIO
A3: CÁLCULO PUNTO DE EQUILIBRIO OPERACIONAL
A5: Costos fijos anuales (Año 1) | B5: ='Costos Operacionales'!B9 -> 10000000
A6: Ingreso por cliente/año | B6: =Supuestos!B19 -> 216000
A8: PUNTO DE EQUILIBRIO | B8: =ROUNDUP(B5/B6,0) -> 47 | C8: farmacias
A9: Fórmula: Costos Fijos / Ingreso por cliente
A11: MARGEN DE SEGURIDAD AÑO 1
A13: Clientes proyectados Año 1 | B13: =Supuestos!B24 -> 35
A14: Punto de equilibrio | B14: =B8 -> 47
A15: Margen de seguridad | B15: =B13-B8 -> -12 | C15: clientes sobre equilibrio
A16: Margen de seguridad % | B16: =(B13-B14)/B13 -> -0.34285714

Sheet Métricas SaaS
A1: MÉTRICAS CLAVE SAAS
A3: MÉTRICAS DE UNIT ECONOMICS
A4: Métrica | B4: Valor | C4: Benchmark | D4: Estado
A5: CAC (Costo Adquisición Cliente) | B5: 350000 | C5: Variable | D5: Input
A6: Vida promedio cliente (años) | B6: =1/(1-Supuestos!B17) -> 5 | C6: 3-5 años | D6: =IF(B6>=3,"OK","BAJO") -> OK
A7: LTV (Valor Vida Cliente) | B7: =Supuestos!B19*B6 -> 1080000 | C7: > 3× CAC | D7: =IF(B7>3*B5,"OK","REVISAR") -> OK
A8: Ratio LTV/CAC | B8: =B7/B5 -> 3.0857143 | C8: > 3.0 | D8: =IF(B8>=3,"SALUDABLE",IF(B8>=2,"ACEPTABLE","CRÍTICO")) -> SALUDABLE
A9: Meses para recuperar CAC | B9: =B5/(Supuestos!B15) -> 19.444444 | C9: < 12 meses | D9: =IF(B9<=12,"OK","LENTO") -> LENTO
A11: NOTA: CAC de $800k asume costo marketing + tiempo comercial
A12: Nota: CAC considera costo promedio incluyendo
A13: esfuerzo comercial del equipo fundador.
A14: El Año 1 incluye costos one-time de lanzamiento.
